{
  "3d": [
    {
      "title": "3D",
      "description": "",
      "background": "categories/background.jpg"
    }
  ],
  "charadesign": [
    {
      "title": "Chara Design",
      "description": "",
      "background": "categories/background.jpg"
    }
  ],
  "oldschool": [
    {
      "title": "Old School",
      "description": "",
      "background": "categories/background.jpg"
    }
  ],
  "illustration": [
    {
      "title": "Illustration",
      "description": "",
      "background": "categories/background.jpg"
    }
  ],
  "conceptart": [
    {
      "title": "Concept Art",
      "description": "",
      "background": "categories/background.jpg"
    }
  ]
}
